mfd_event_log/__init__.py
mfd_event_log/base.py
mfd_event_log/data_structures.py
mfd_event_log/exceptions.py
mfd_event_log-0.9.0.dist-info/licenses/AUTHORS.md
mfd_event_log-0.9.0.dist-info/licenses/LICENSE.md
mfd_event_log-0.9.0.dist-info/METADATA
mfd_event_log-0.9.0.dist-info/WHEEL
mfd_event_log-0.9.0.dist-info/top_level.txt
mfd_event_log-0.9.0.dist-info/RECORD
