Metadata-Version: 2.4
Name: mfd-event-log
Version: 0.9.0
Summary: Module for event logs handling
Project-URL: Homepage, https://github.com/intel/mfd
Project-URL: Repository, https://github.com/intel/mfd-event-log
Project-URL: Issues, https://github.com/intel/mfd-event-log/issues
Project-URL: Changelog, https://github.com/intel/mfd-event-log/blob/main/CHANGELOG.md
Requires-Python: <3.14,>=3.10
License-File: LICENSE.md
License-File: AUTHORS.md
Requires-Dist: mfd-common-libs>=1.11.0
Requires-Dist: mfd-typing>=1.23.0
Dynamic: license-file
